odoo/addons/account_statement_import_ofx_by_acctid/README.rst
odoo/addons/account_statement_import_ofx_by_acctid/__init__.py
odoo/addons/account_statement_import_ofx_by_acctid/__manifest__.py
odoo/addons/account_statement_import_ofx_by_acctid/i18n/account_statement_import_ofx_by_acctid.pot
odoo/addons/account_statement_import_ofx_by_acctid/i18n/es.po
odoo/addons/account_statement_import_ofx_by_acctid/i18n/it.po
odoo/addons/account_statement_import_ofx_by_acctid/models/__init__.py
odoo/addons/account_statement_import_ofx_by_acctid/models/res_partner_bank.py
odoo/addons/account_statement_import_ofx_by_acctid/readme/CONTRIBUTORS.rst
odoo/addons/account_statement_import_ofx_by_acctid/readme/DESCRIPTION.rst
odoo/addons/account_statement_import_ofx_by_acctid/readme/USAGE.rst
odoo/addons/account_statement_import_ofx_by_acctid/static/description/icon.png
odoo/addons/account_statement_import_ofx_by_acctid/static/description/index.html
odoo/addons/account_statement_import_ofx_by_acctid/tests/__init__.py
odoo/addons/account_statement_import_ofx_by_acctid/tests/test_import_bank_statement.py
odoo/addons/account_statement_import_ofx_by_acctid/tests/test_ofx_file/test_ofx.ofx
odoo/addons/account_statement_import_ofx_by_acctid/tests/test_ofx_file/test_ofx_iban.ofx
odoo/addons/account_statement_import_ofx_by_acctid/tests/test_ofx_file/test_ofx_wrong.ofx
odoo/addons/account_statement_import_ofx_by_acctid/views/res_partner_bank.xml
odoo/addons/account_statement_import_ofx_by_acctid/wizards/__init__.py
odoo/addons/account_statement_import_ofx_by_acctid/wizards/account_statement_import.py
odoo14_addon_account_statement_import_ofx_by_acctid-14.0.1.0.1.dev10.dist-info/METADATA
odoo14_addon_account_statement_import_ofx_by_acctid-14.0.1.0.1.dev10.dist-info/WHEEL
odoo14_addon_account_statement_import_ofx_by_acctid-14.0.1.0.1.dev10.dist-info/top_level.txt
odoo14_addon_account_statement_import_ofx_by_acctid-14.0.1.0.1.dev10.dist-info/RECORD
