Metadata-Version: 2.1
Name: odoo14-addon-account_statement_import_ofx_by_acctid
Version: 14.0.1.0.1.dev10
Summary: Import OFX Bank Statement by ACCTID
Home-page: https://github.com/OCA/bank-statement-import
Author: Escodoo,Odoo Community Association (OCA)
Author-email: support@odoo-community.org
License: AGPL-3
Classifier: Programming Language :: Python
Classifier: Framework :: Odoo
Classifier: Framework :: Odoo :: 14.0
Classifier: License :: OSI Approved :: GNU Affero General Public License v3
Requires-Python: >=3.6
Requires-Dist: odoo14-addon-account-statement-import-ofx
Requires-Dist: odoo<14.1dev,>=14.0a
